[
{
  "model": "track.track",
  "pk": 1,
  "fields": {
    "created_at": "2017-07-29T02:34:07.701Z",
    "updated_at": "2017-07-29T02:34:07.701Z",
    "gateway_id": 335192127,
    "title": "Remember When",
    "stream_url": "https://api.soundcloud.com/tracks/335192127/stream",
    "artwork_url": "https://i1.sndcdn.com/artworks-000235562915-1ao6et-large.jpg",
    "username": "OXILO",
    "archived": false
  }
},
{
  "model": "track.track",
  "pk": 2,
  "fields": {
    "created_at": "2017-07-29T02:34:07.701Z",
    "updated_at": "2017-07-29T02:34:07.701Z",
    "gateway_id": 335247852,
    "title": "Sean Paul - No Lie Ft. Dua Lipa (Mark Melgo Remix)[Free DL = Buy]",
    "stream_url": "https://api.soundcloud.com/tracks/335247852/stream",
    "artwork_url": "https://i1.sndcdn.com/artworks-000235618620-se21cv-large.jpg",
    "username": "Mark Melgo Treasures",
    "archived": false
  }
},
{
  "model": "track.track",
  "pk": 3,
  "fields": {
    "created_at": "2017-07-29T02:34:07.701Z",
    "updated_at": "2017-07-29T02:34:07.701Z",
    "gateway_id": 335318092,
    "title": "MAJOR LAZER x FLOSSTRADAMUS - ORIGNAL DON (PARTY FAVOR EDIT) * CLICK BUY",
    "stream_url": "https://api.soundcloud.com/tracks/335318092/stream",
    "artwork_url": "https://i1.sndcdn.com/artworks-000235706475-39b1pp-large.jpg",
    "username": "PARTY FAVOR",
    "archived": false
  }
},
{
  "model": "track.track",
  "pk": 4,
  "fields": {
    "created_at": "2017-07-29T02:34:07.701Z",
    "updated_at": "2017-07-29T02:34:07.701Z",
    "gateway_id": 335317851,
    "title": "ROLEX (PARTY FAVOR REMIX)",
    "stream_url": "https://api.soundcloud.com/tracks/335317851/stream",
    "artwork_url": "https://i1.sndcdn.com/artworks-000235706263-n50ntc-large.jpg",
    "username": "PARTY FAVOR",
    "archived": false
  }
},
{
  "model": "track.track",
  "pk": 5,
  "fields": {
    "created_at": "2017-07-29T02:34:07.701Z",
    "updated_at": "2017-07-29T02:34:07.701Z",
    "gateway_id": 334930438,
    "title": "Skrillex & Poo Bear - Would You Ever",
    "stream_url": "https://api.soundcloud.com/tracks/334930438/stream",
    "artwork_url": "https://i1.sndcdn.com/artworks-000235280255-5fyldq-large.jpg",
    "username": "Skrillex",
    "archived": false
  }
},
{
  "model": "track.track",
  "pk": 6,
  "fields": {
    "created_at": "2017-07-29T02:34:07.701Z",
    "updated_at": "2017-07-29T02:34:07.701Z",
    "gateway_id": 335242317,
    "title": "You'll Never Know ft. Moza (Lay-Wy Remix)",
    "stream_url": "https://api.soundcloud.com/tracks/335242317/stream",
    "artwork_url": "https://i1.sndcdn.com/artworks-000235615446-8qism8-large.jpg",
    "username": "Lay-Wy",
    "archived": false
  }
},
{
  "model": "track.track",
  "pk": 7,
  "fields": {
    "created_at": "2017-07-29T02:34:07.701Z",
    "updated_at": "2017-07-29T02:34:07.701Z",
    "gateway_id": 335265115,
    "title": "Copycat (Original Mix)",
    "stream_url": "https://api.soundcloud.com/tracks/335265115/stream",
    "artwork_url": "https://i1.sndcdn.com/artworks-000235639172-uvs3dx-large.jpg",
    "username": "MineSweepa",
    "archived": false
  }
},
{
  "model": "track.track",
  "pk": 8,
  "fields": {
    "created_at": "2017-07-29T02:34:07.701Z",
    "updated_at": "2017-07-29T02:34:07.701Z",
    "gateway_id": 335240714,
    "title": "Savoy & Grabbitz - Contemplate",
    "stream_url": "https://api.soundcloud.com/tracks/335240714/stream",
    "artwork_url": "https://i1.sndcdn.com/artworks-000235612368-ok5zoj-large.jpg",
    "username": "Monstercat",
    "archived": false
  }
}
]
